quantiprot/__init__.py
quantiprot/analysis/__init__.py
quantiprot/analysis/fisher.py
quantiprot/analysis/ngram.py
quantiprot/metrics/__init__.py
quantiprot/metrics/aaindex.py
quantiprot/metrics/alphabet.py
quantiprot/metrics/basic.py
quantiprot/metrics/entropy.py
quantiprot/metrics/ngram.py
quantiprot/metrics/rqa.py
quantiprot/utils/__init__.py
quantiprot/utils/feature.py
quantiprot/utils/io.py
quantiprot/utils/mapping.py
quantiprot/utils/sequence.py
quantiprot-0.2.5.dist-info/LICENSE.txt
quantiprot-0.2.5.dist-info/METADATA
quantiprot-0.2.5.dist-info/WHEEL
quantiprot-0.2.5.dist-info/top_level.txt
quantiprot-0.2.5.dist-info/RECORD
