Metadata-Version: 2.1
Name: quantiprot
Version: 0.2.5
Summary: Quantitative characteristics of protein sequences
Author: Witold Dyrka, Bogumil M. Konopka, Marta Marciniak
Author-email: witold.dyrka@pwr.edu.pl
Project-URL: Homepage, https://git.e-science.pl/wdyrka/quantiprot/
Project-URL: Bug Tracker, https://git.e-science.pl/wdyrka/quantiprot/-/issues
Keywords: protein,sequence,quantitative,analysis,rqa,n-gram
Classifier: Programming Language :: Python
Classifier: License :: OSI Approved :: MIT License
Classifier: Operating System :: OS Independent
Requires-Python: >=2.7
License-File: LICENSE.txt
